<?xml version="1.0" encoding="utf-8"?>
<pinyin xmlns:xsi="http://www.w3.org/2001/XMLSchema-instance" xsi:noNamespaceSchemaLocation="../pinyin.cshtml">
	<!-- Ref:闶.xml <char hz="闶" py="kāng" multi="kàng" /> -->
	<char hz="康" py="kāng" />
	<char hz="慷" py="kāng">
		<phrase hz="慷慨" py="kāng,kǎi" />
	</char>
	<char hz="槺" py="kāng" />
	<char hz="鱇" py="kāng" trans="1" />
	<!-- Ref:扛.xml <char hz="扛" py="káng" multi="gāng" main="1" suppressLog="1" /> -->
	<char hz="亢" py="kàng" />
	<char hz="伉" py="kàng">
		<phrase hz="伉俪" py="kàng,lì" />
	</char>
	<char hz="抗" py="kàng" />
	<!-- Ref:闶.xml <char hz="闶" py="kàng" multi="kāng" main="1" /> -->
	<char hz="炕" py="kàng" />
	<char hz="钪" py="kàng" />
</pinyin>
