<?xml version="1.0" encoding="utf-8"?>
<pinyin xmlns:xsi="http://www.w3.org/2001/XMLSchema-instance" xsi:noNamespaceSchemaLocation="../pinyin.cshtml">
	<char hz="良" py="liáng" />
	<char hz="粮" py="liáng" />
	<!-- Ref:踉.xml <char hz="踉" py="liáng" multi="liàng" main="1" /> -->
	<!-- Ref:凉.xml <char hz="凉" py="liáng" multi="liàng" main="1" /> -->
	<char hz="椋" py="liáng" />
	<char hz="辌" py="liáng" />
	<char hz="梁" py="liáng" />
	<char hz="粱" py="liáng" />
	<!-- Ref:量.xml <char hz="量" py="liáng" multi="liàng" /> -->
	<char hz="两" py="liǎng" />
	<!-- Ref:俩.xml <char hz="俩" py="liǎng" multi="liǎ" info="Word主音" /> -->
	<char hz="唡" py="liǎng" />
	<char hz="緉" py="liǎng" trans="1" />
	<char hz="魉" py="liǎng" />
	<char hz="亮" py="liàng" />
	<char hz="喨" py="liàng" />
	<!-- Ref:倞.xml <char hz="倞" py="liàng" multi="jìng" main="1" /> -->
	<!-- Ref:凉.xml <char hz="凉" py="liàng" multi="liáng" /> -->
	<char hz="谅" py="liàng" />
	<char hz="晾" py="liàng" />
	<char hz="悢" py="liàng" />
	<!-- Ref:踉.xml <char hz="踉" py="liàng" multi="liáng" /> -->
	<char hz="辆" py="liàng" />
	<!-- Ref:靓.xml <char hz="靓" py="liàng" multi="jìng" /> -->
	<!-- Ref:量.xml <char hz="量" py="liàng" multi="liáng" main="1" /> -->
</pinyin>
